pyiota/__init__.py
pyiota/iota.py
pyiota-1.2.1.dist-info/METADATA
pyiota-1.2.1.dist-info/WHEEL
pyiota-1.2.1.dist-info/top_level.txt
pyiota-1.2.1.dist-info/RECORD
