Metadata-Version: 2.1
Name: pyiota
Version: 1.2.1
Summary: Simple Go lang iota pattern implementation
Author: @jedi2light
Author-email: jedi2light@jedi2light.moe
Maintainer: @jedi2light
Maintainer-email: jedi2light@jedi2light.moe
License: WTFPL
Project-URL: Documentation, https://gitlab.com/jedi2light/pyiota.git
Project-URL: Bug Tracker, https://gitlab.com/jedi2light/pyiota/issues
Classifier: Programming Language :: Python :: 3
Classifier: Operating System :: OS Independent
Requires-Python: >=3.6
